launch.py
script.js
style.css
webui.py
webui_hook.py
webui_wrapper.py
configs/alt-diffusion-inference.yaml
configs/instruct-pix2pix.yaml
configs/v1-inference.yaml
configs/v1-inpainting-inference.yaml
extensions-builtin/LDSR/ldsr_model_arch.py
extensions-builtin/LDSR/preload.py
extensions-builtin/LDSR/sd_hijack_autoencoder.py
extensions-builtin/LDSR/sd_hijack_ddpm_v1.py
extensions-builtin/LDSR/scripts/ldsr_model.py
extensions-builtin/Lora/extra_networks_lora.py
extensions-builtin/Lora/lora.py
extensions-builtin/Lora/preload.py
extensions-builtin/Lora/ui_extra_networks_lora.py
extensions-builtin/Lora/scripts/lora_script.py
extensions-builtin/ScuNET/preload.py
extensions-builtin/ScuNET/scunet_model_arch.py
extensions-builtin/ScuNET/scripts/scunet_model.py
extensions-builtin/SwinIR/preload.py
extensions-builtin/SwinIR/swinir_model_arch.py
extensions-builtin/SwinIR/swinir_model_arch_v2.py
extensions-builtin/SwinIR/scripts/swinir_model.py
extensions-builtin/prompt-bracket-checker/javascript/prompt-bracket-checker.js
html/extra-networks-card.html
html/extra-networks-no-cards.html
html/footer.html
html/image-update.svg
html/licenses.html
javascript/aspectRatioOverlay.js
javascript/contextMenus.js
javascript/dragdrop.js
javascript/edit-attention.js
javascript/extensions.js
javascript/extraNetworks.js
javascript/generationParams.js
javascript/hints.js
javascript/hires_fix.js
javascript/imageMaskFix.js
javascript/imageParams.js
javascript/imageviewer.js
javascript/imageviewerGamepad.js
javascript/localization.js
javascript/notification.js
javascript/progressbar.js
javascript/textualInversion.js
javascript/ui.js
javascript/ui_settings_hints.js
localizations/Put localization files here.txt
models/VAE-approx/model.pt
models/karlo/ViT-L-14_stats.th
modules/__init__.py
modules/call_queue.py
modules/cmd_args.py
modules/codeformer_model.py
modules/config_states.py
modules/deepbooru.py
modules/deepbooru_model.py
modules/devices.py
modules/errors.py
modules/esrgan_model.py
sdwebui-0.0.7.dist-info/LICENSE.txt
sdwebui-0.0.7.dist-info/METADATA
sdwebui-0.0.7.dist-info/WHEEL
sdwebui-0.0.7.dist-info/top_level.txt
sdwebui-0.0.7.dist-info/RECORD
