Metadata-Version: 2.1
Name: sdwebui
Version: 0.0.7
Summary: Stable diffusion webui package
Author: tangjicheng
Author-email: tang.j@ctw.inc
License-File: LICENSE.txt
